summon_python/__init__.py
summon_python/plugin.py
summon_python/project.py
summon_python/tasks.py
summon_python-0.2.1.dist-info/entry_points.txt
summon_python-0.2.1.dist-info/WHEEL
summon_python-0.2.1.dist-info/METADATA
summon_python-0.2.1.dist-info/RECORD
