Metadata-Version: 2.1
Name: summon-python
Version: 0.2.1
Summary: A collection of Python project-related tasks for Summon.
Author: Tarcísio Eduardo Moreira Crocomo
Author-email: tarcisioe@pm.me
Requires-Python: >=3.7,<4.0
Classifier: Programming Language :: Python :: 3
Classifier: Programming Language :: Python :: 3.10
Classifier: Programming Language :: Python :: 3.7
Classifier: Programming Language :: Python :: 3.8
Classifier: Programming Language :: Python :: 3.9
Provides-Extra: core
Requires-Dist: summon-tasks (>=0.2.0,<0.3.0); extra == "core"
Requires-Dist: toml (>=0.10.2,<0.11.0)
